mynlpwrangler/__init__.py
mynlpwrangler/cleaner.py
mynlpwrangler/tokenizer.py
my_nlp_wrangler-0.0.3.dist-info/LICENSE
my_nlp_wrangler-0.0.3.dist-info/METADATA
my_nlp_wrangler-0.0.3.dist-info/WHEEL
my_nlp_wrangler-0.0.3.dist-info/top_level.txt
my_nlp_wrangler-0.0.3.dist-info/RECORD
