Metadata-Version: 2.1
Name: my-nlp-wrangler
Version: 0.0.3
Summary: UNKNOWN
Home-page: https://github.com/jjudy60334/my-nlp-wrangler
Author: Claire.Wu
Author-email: jjudy708618@gmail.com
License: UNKNOWN
Platform: UNKNOWN
Classifier: Programming Language :: Python :: 3
Classifier: Development Status :: 1 - Planning
Requires-Python: >=3.7
Requires-Dist: flake8 (==3.8.4)
Requires-Dist: jieba (==0.42.1)
Requires-Dist: mccabe (==0.6.1)
Requires-Dist: numpy (==1.20.1)
Requires-Dist: pandas (==1.2.3)
Requires-Dist: pycodestyle (==2.6.0)
Requires-Dist: pyflakes (==2.2.0)
Requires-Dist: python-dateutil (==2.8.1)
Requires-Dist: pytz (==2021.1)
Requires-Dist: six (==1.15.0)
